pyx2cscope/__init__.py
pyx2cscope/__main__.py
pyx2cscope/examples/SFR_Example.py
pyx2cscope/examples/demo.py
pyx2cscope/examples/exampleMCAF.py
pyx2cscope/examples/export_import_variables.py
pyx2cscope/examples/get_device_id.py
pyx2cscope/examples/live_scope.py
pyx2cscope/examples/minimal_gui.py
pyx2cscope/examples/plotting_and_saving.py
pyx2cscope/examples/pyX2CScope_demo.py
pyx2cscope/examples/simplest.py
pyx2cscope/examples/simplest_no_elf.py
pyx2cscope/examples/testingArray.py
pyx2cscope/gui/__init__.py
pyx2cscope/gui/generic_gui/__init__.py
pyx2cscope/gui/generic_gui/detachable_gui.py
pyx2cscope/gui/generic_gui/generic_gui.py
pyx2cscope/gui/img/__init__.py
pyx2cscope/gui/img/pyx2cscope.ico
pyx2cscope/gui/img/pyx2cscope.jpg
pyx2cscope/gui/img/refresh.png
pyx2cscope/gui/watchView/__init__.py
pyx2cscope/gui/watchView/minimal_gui.py
pyx2cscope/gui/web/__init__.py
pyx2cscope/gui/web/app.py
pyx2cscope/gui/web/static/css/bootstrap.min.css
pyx2cscope/gui/web/static/css/dataTables.bootstrap5.css
pyx2cscope/gui/web/static/css/flUhRq6tzZclQEJ-Vdg-IuiaDsNc.woff2
pyx2cscope/gui/web/static/css/icon.css
pyx2cscope/gui/web/static/css/select2.min.css
pyx2cscope/gui/web/static/css/style.css
pyx2cscope/gui/web/static/favicon.ico
pyx2cscope/gui/web/static/js/bootstrap.bundle.min.js
pyx2cscope/gui/web/static/js/chart.js
pyx2cscope/gui/web/static/js/chartjs-plugin-zoom.js
pyx2cscope/gui/web/static/js/dataTables.bootstrap4.min.js
pyx2cscope/gui/web/static/js/hammer.min.js
pyx2cscope/gui/web/static/js/jquery-3.5.1.min.js
pyx2cscope/gui/web/static/js/jquery.dataTables.min.js
pyx2cscope/gui/web/static/js/qrcode.min.js
pyx2cscope/gui/web/static/js/scope_view.js
pyx2cscope/gui/web/static/js/script.js
pyx2cscope/gui/web/static/js/select2.min.js
pyx2cscope/gui/web/static/js/watch_view.js
pyx2cscope/gui/web/static/microchip-logo.png
pyx2cscope/gui/web/templates/base.html
pyx2cscope/gui/web/templates/footer.html
pyx2cscope/gui/web/templates/header.html
pyx2cscope/gui/web/templates/index.html
pyx2cscope-0.4.4.dist-info/LICENSE
pyx2cscope-0.4.4.dist-info/METADATA
pyx2cscope-0.4.4.dist-info/WHEEL
pyx2cscope-0.4.4.dist-info/entry_points.txt
pyx2cscope-0.4.4.dist-info/RECORD
