Metadata-Version: 2.1
Name: pyx2cscope
Version: 0.4.4
Summary: python implementation of X2Cscope
Home-page: https://x2cscope.github.io/
License: Proprietary
Author: Yash Agarwal
Requires-Python: >=3.10,<4.0
Classifier: License :: Other/Proprietary License
Classifier: Programming Language :: Python :: 3
Classifier: Programming Language :: Python :: 3.10
Classifier: Programming Language :: Python :: 3.11
Classifier: Programming Language :: Python :: 3.12
Requires-Dist: PyQt5 (>=5.15.9,<6.0.0)
Requires-Dist: flask (>=3.0.3,<4.0.0)
Requires-Dist: matplotlib (>=3.7.2,<4.0.0)
Requires-Dist: mchplnet (==0.2.1)
Requires-Dist: numpy (>=1.26.0,<2.0.0)
Requires-Dist: pyelftools (>=0.31,<0.32)
Requires-Dist: pyqtgraph (>=0.13.7,<0.14.0)
Requires-Dist: pyserial (>=3.5,<4.0)
Requires-Dist: pyyaml (>=6.0.1,<7.0.0)
Project-URL: Documentation, https://x2cscope.github.io/pyx2cscope
Project-URL: Repository, https://github.com/X2Cscope/pyx2cscope
